MANIFEST.in
README.md
README.rst
setup.py
chainz/__init__.py
chainz/chain.py
chainz/utils.py
chainz.egg-info/PKG-INFO
chainz.egg-info/SOURCES.txt
chainz.egg-info/dependency_links.txt
chainz.egg-info/not-zip-safe
chainz.egg-info/top_level.txt