Metadata-Version: 1.0
Name: chainz
Version: 0.14
Summary: Lightweight chaining functional methods for iterables
Home-page: http://github.com/jagill/python-chainz
Author: James Gill
Author-email: jamesagill@gmail.com
License: MIT
Keywords: iterable generators functional map filter reduce
Platform: UNKNOWN
